{ "CommonCardLeveling":
[
  {
    "level": "1",
    "cardsNeeded": "1",
    "cost": "0",
    "xp": "0"
  },
  {
    "level": "2",
    "cardsNeeded": "15",
    "cost": "20",
    "xp": "100"
  },
  {
    "level": "3",
    "cardsNeeded": "35",
    "cost": "60",
    "xp": "110"
  },
  {
    "level": "4",
    "cardsNeeded": "60",
    "cost": "200",
    "xp": "120"
  },
  {
    "level": "5",
    "cardsNeeded": "90",
    "cost": "425",
    "xp": "130"
  },
  {
    "level": "6",
    "cardsNeeded": "145",
    "cost": "600",
    "xp": "140"
  },
  {
    "level": "7",
    "cardsNeeded": "220",
    "cost": "800",
    "xp": "150"
  },
  {
    "level": "8",
    "cardsNeeded": "300",
    "cost": "1100",
    "xp": "160"
  },
  {
    "level": "9",
    "cardsNeeded": "400",
    "cost": "1800",
    "xp": "170"
  },
  {
    "level": "10",
    "cardsNeeded": "600",
    "cost": "2200",
    "xp": "180"
  },
  {
    "level": "11",
    "cardsNeeded": "0",
    "cost": "0",
    "xp": "190"
  }
]
}